travel_pii_anonymisation-0.3.3.dist-info/licenses/LICENSE
tspii/__init__.py
tspii/tspii.py
tspii/anonymizers/__init__.py
tspii/anonymizers/instance_counter_anonymizer.py
tspii/deanonymizers/__init__.py
tspii/deanonymizers/instance_counter_deanonymizer.py
tspii/helpers/__init__.py
tspii/helpers/helpers.py
tspii/operators/__init__.py
tspii/operators/faker_operators.py
tspii/recognizers/__init__.py
tspii/recognizers/recognizers.py
tspii/reversible_anonymizers/__init__.py
tspii/reversible_anonymizers/reversible_anonymizer.py
travel_pii_anonymisation-0.3.3.dist-info/METADATA
travel_pii_anonymisation-0.3.3.dist-info/WHEEL
travel_pii_anonymisation-0.3.3.dist-info/entry_points.txt
travel_pii_anonymisation-0.3.3.dist-info/top_level.txt
travel_pii_anonymisation-0.3.3.dist-info/RECORD
