Metadata-Version: 2.4
Name: travel_pii_anonymisation
Version: 0.3.3
Summary: A package for pseudonymizing travel-specific PII data
Home-page: https://github.com/AmadeusITGroup/Travel-specific-PIIs-pseudonymization
Author: Ilias
Author-email: ilias.driouich@amadeus.com
Requires-Python: >=3.6
License-File: LICENSE
Requires-Dist: presidio-analyzer==2.2.358
Requires-Dist: presidio-anonymizer==2.2.358
Requires-Dist: faker==20.1.0
Dynamic: author
Dynamic: author-email
Dynamic: description
Dynamic: description-content-type
Dynamic: home-page
Dynamic: license-file
Dynamic: requires-dist
Dynamic: requires-python
Dynamic: summary
